shimbboleth/__init__.py
shimbboleth/py.typed
shimbboleth/buildkite/__init__.py
shimbboleth/buildkite/agent.py
shimbboleth/buildkite/agent_test.py
shimbboleth-0.0.1.dist-info/METADATA
shimbboleth-0.0.1.dist-info/WHEEL
shimbboleth-0.0.1.dist-info/licenses/LICENSE
shimbboleth-0.0.1.dist-info/RECORD
